<!--Erzeugt mit KIT (www.kit.edu) UmlToXmlTransformation-Software, Erstellungsdatum: 03.07.2019 08:18:28-->
<TypeDefinition xmlns="http://www.interactive-instruments.de/ShapeChange/Definitions/0.5" xmlns:def="http://www.interactive-instruments.de/ShapeChange/Definitions/0.5" xmlns:gml="http://www.opengis.net/gml/3.2" xmlns:xlink="http://www.w3.org/1999/xlink" xmlns:xsi="http://www.w3.org/2001/XMLSchema-instance" xsi:schemaLocation="http://www.interactive-instruments.de/ShapeChange/Definitions/0.5 ../xsd/ShapeChangeDefinitions.xsd" gml:id="xplan_RP_WohnenSiedlung">
  <gml:description>Wohn- und Siedlungsstruktur und -funktionen.</gml:description>
  <gml:identifier codeSpace="urn:xplan">urn:xplan:element:xplan:RP_WohnenSiedlung</gml:identifier>
  <gml:name>xplan:RP_WohnenSiedlung</gml:name>
  <gml:dictionaryEntry>
    <def:PropertyDefinition gml:id="xplan_RP_WohnenSiedlung_typ">
      <gml:description>Klassifikation von Wohnen- und Siedlungstypen.</gml:description>
      <gml:identifier codeSpace="urn:xplan">urn:xplan:element:xplan:RP_WohnenSiedlung:attribute:typ</gml:identifier>
      <gml:name>xplan:typ</gml:name>
      <gml:dictionaryEntry>
        <ListedValueDefinition gml:id="xplan_RP_WohnenSiedlung_typ_RP_WohnenSiedlungTypen_1000">
          <gml:description>Wohnen</gml:description>
          <gml:identifier codeSpace="urn:xplan">urn:xplan:enum:xplan:RP_WohnenSiedlung:typ:RP_WohnenSiedlungTypen:1000</gml:identifier>
          <gml:name>Wohnen</gml:name>
        </ListedValueDefinition>
      </gml:dictionaryEntry>
      <gml:dictionaryEntry>
        <ListedValueDefinition gml:id="xplan_RP_WohnenSiedlung_typ_RP_WohnenSiedlungTypen_2000">
          <gml:description>Baugebietsgrenze.</gml:description>
          <gml:identifier codeSpace="urn:xplan">urn:xplan:enum:xplan:RP_WohnenSiedlung:typ:RP_WohnenSiedlungTypen:2000</gml:identifier>
          <gml:name>Baugebietsgrenze</gml:name>
        </ListedValueDefinition>
      </gml:dictionaryEntry>
      <gml:dictionaryEntry>
        <ListedValueDefinition gml:id="xplan_RP_WohnenSiedlung_typ_RP_WohnenSiedlungTypen_3000">
          <gml:description>Siedlungsgebiet.</gml:description>
          <gml:identifier codeSpace="urn:xplan">urn:xplan:enum:xplan:RP_WohnenSiedlung:typ:RP_WohnenSiedlungTypen:3000</gml:identifier>
          <gml:name>Siedlungsgebiet</gml:name>
        </ListedValueDefinition>
      </gml:dictionaryEntry>
      <gml:dictionaryEntry>
        <ListedValueDefinition gml:id="xplan_RP_WohnenSiedlung_typ_RP_WohnenSiedlungTypen_3001">
          <gml:description>Siedlungsschwerpunkt.</gml:description>
          <gml:identifier codeSpace="urn:xplan">urn:xplan:enum:xplan:RP_WohnenSiedlung:typ:RP_WohnenSiedlungTypen:3001</gml:identifier>
          <gml:name>Siedlungsschwerpunkt</gml:name>
        </ListedValueDefinition>
      </gml:dictionaryEntry>
      <gml:dictionaryEntry>
        <ListedValueDefinition gml:id="xplan_RP_WohnenSiedlung_typ_RP_WohnenSiedlungTypen_3002">
          <gml:description>Siedlungsentwicklung.</gml:description>
          <gml:identifier codeSpace="urn:xplan">urn:xplan:enum:xplan:RP_WohnenSiedlung:typ:RP_WohnenSiedlungTypen:3002</gml:identifier>
          <gml:name>Siedlungsentwicklung</gml:name>
        </ListedValueDefinition>
      </gml:dictionaryEntry>
      <gml:dictionaryEntry>
        <ListedValueDefinition gml:id="xplan_RP_WohnenSiedlung_typ_RP_WohnenSiedlungTypen_3003">
          <gml:description>Siedlungsbeschränkung.</gml:description>
          <gml:identifier codeSpace="urn:xplan">urn:xplan:enum:xplan:RP_WohnenSiedlung:typ:RP_WohnenSiedlungTypen:3003</gml:identifier>
          <gml:name>Siedlungsbeschraenkung</gml:name>
        </ListedValueDefinition>
      </gml:dictionaryEntry>
      <gml:dictionaryEntry>
        <ListedValueDefinition gml:id="xplan_RP_WohnenSiedlung_typ_RP_WohnenSiedlungTypen_3004">
          <gml:description>Sonstige WohnenSiedlungstypen.</gml:description>
          <gml:identifier codeSpace="urn:xplan">urn:xplan:enum:xplan:RP_WohnenSiedlung:typ:RP_WohnenSiedlungTypen:3004</gml:identifier>
          <gml:name>Siedlungsnutzung</gml:name>
        </ListedValueDefinition>
      </gml:dictionaryEntry>
      <gml:dictionaryEntry>
        <ListedValueDefinition gml:id="xplan_RP_WohnenSiedlung_typ_RP_WohnenSiedlungTypen_4000">
          <gml:description>Sicherung der Entwicklung von Wohnstätten</gml:description>
          <gml:identifier codeSpace="urn:xplan">urn:xplan:enum:xplan:RP_WohnenSiedlung:typ:RP_WohnenSiedlungTypen:4000</gml:identifier>
          <gml:name>SicherungEntwicklungWohnstaetten</gml:name>
        </ListedValueDefinition>
      </gml:dictionaryEntry>
      <gml:dictionaryEntry>
        <ListedValueDefinition gml:id="xplan_RP_WohnenSiedlung_typ_RP_WohnenSiedlungTypen_5000">
          <gml:description>Allgemeiner Siedlungsbereich</gml:description>
          <gml:identifier codeSpace="urn:xplan">urn:xplan:enum:xplan:RP_WohnenSiedlung:typ:RP_WohnenSiedlungTypen:5000</gml:identifier>
          <gml:name>AllgemeinerSiedlungsbereichASB</gml:name>
        </ListedValueDefinition>
      </gml:dictionaryEntry>
      <gml:dictionaryEntry>
        <ListedValueDefinition gml:id="xplan_RP_WohnenSiedlung_typ_RP_WohnenSiedlungTypen_9999">
          <gml:description>Sonstiges</gml:description>
          <gml:identifier codeSpace="urn:xplan">urn:xplan:enum:xplan:RP_WohnenSiedlung:typ:RP_WohnenSiedlungTypen:9999</gml:identifier>
          <gml:name>SonstigeWohnenSiedlung</gml:name>
        </ListedValueDefinition>
      </gml:dictionaryEntry>
      <def:cardinality>0..*</def:cardinality>
      <def:valueTypeName>RP_WohnenSiedlungTypen</def:valueTypeName>
      <def:type>attribute</def:type>
    </def:PropertyDefinition>
  </gml:dictionaryEntry>
  <def:classification>featureType</def:classification>
  <def:supertypeRef xlink:href="urn:xplan:element:xplan:RP_Siedlung" />
</TypeDefinition>